defe/__init__.py
defe/__main__.py
defe/defe.py
defe/formatter.py
defe/core/__init__.py
defe/core/feed.py
defe/core/feedcore.py
defe/core/feeders/general.json
defe/core/feeders/news.json
defe/core/feeders/newsletters.json
defe/core/feeders/podcasts.json
defe-0.0.1.dist-info/LICENSE
defe-0.0.1.dist-info/METADATA
defe-0.0.1.dist-info/WHEEL
defe-0.0.1.dist-info/entry_points.txt
defe-0.0.1.dist-info/top_level.txt
defe-0.0.1.dist-info/RECORD
