Metadata-Version: 2.1
Name: defe
Version: 0.0.1
Summary: A Tech feed Aggregator for Developers.
Home-page: https://github.com/Bhupesh-V/defe
Author: Bhupesh Varshney
Author-email: varshneybhupesh@gmail.com
License: GPLv2
Project-URL: Documentation, https://defe.readthedocs.io/en/latest/
Project-URL: Source Code, https://github.com/Bhupesh-V/defe
Project-URL: Funding, https://www.patreon.com/bePatron?u=18082750
Project-URL: Say Thanks!, https://github.com/Bhupesh-V/defe/issues/new?assignees=&labels=&template=---say-thank-you.md&title=
Project-URL: Tracker, https://github.com/Bhupesh-V/defe/issues
Platform: UNKNOWN
Classifier: Programming Language :: Python :: 3.6
Classifier: Programming Language :: Python :: 3.7
Classifier: Programming Language :: Python :: 3.8
Classifier: License :: OSI Approved :: GNU General Public License v2 (GPLv2)
Classifier: Topic :: Education
Classifier: Topic :: Software Development
Classifier: Topic :: Software Development :: Libraries
Classifier: Topic :: Terminals
Classifier: Topic :: Internet
Classifier: Development Status :: 4 - Beta
Classifier: Intended Audience :: Developers
Classifier: Intended Audience :: Education
Classifier: Intended Audience :: Information Technology
Classifier: Topic :: Utilities
Classifier: Natural Language :: English
Classifier: Operating System :: OS Independent
Requires-Python: >=3.6
Requires-Dist: feedparser
Requires-Dist: colorama
Requires-Dist: tqdm
Requires-Dist: diskcache
